README.rst
setup.py
uwaterlooapi/__init__.py
uwaterlooapi.egg-info/PKG-INFO
uwaterlooapi.egg-info/SOURCES.txt
uwaterlooapi.egg-info/dependency_links.txt
uwaterlooapi.egg-info/not-zip-safe
uwaterlooapi.egg-info/requires.txt
uwaterlooapi.egg-info/top_level.txt