Metadata-Version: 1.1
Name: uwaterlooapi
Version: 0.3.1
Summary: Thin library wrapper for the University of Waterloo Open Data API.
Home-page: https://bitbucket.org/amjoconn/uwaterlooapi
Author: Albert O'Connor
Author-email: info@albertoconnor.ca
License: MIT
Platform: UNKNOWN
Classifier: Development Status :: 3 - Alpha
Classifier: Intended Audience :: Developers
Classifier: Operating System :: OS Independent
